{
  "puzzle": {
    "form": [
      {
        "coord": {
          "x": 0.0,
          "y": 0.0
        }
      },
      {
        "coord": {
          "x": 3.0,
          "y": 0.0
        }
      },
      {
        "coord": {
          "x": 3.0,
          "y": 1.0
        }
      },
      {
        "coord": {
          "x": 0.0,
          "y": 1.0
        }
      }
    ]
  },
  "name": "Puzzle-1r-3c-1848-rot-sol.json",
  "no. of pieces": 3,
  "pieces": [
    {
      "piece": 0,
      "corners": [
        {
          "coord": {
            "x": 0.8231999036866193,
            "y": 1.119689158492872
          }
        },
        {
          "coord": {
            "x": -0.28181229293448706,
            "y": 0.8712162470827083
          }
        },
        {
          "coord": {
            "x": -0.06243021777446078,
            "y": -0.10442277689003177
          }
        },
        {
          "coord": {
            "x": 0.9988859255051658,
            "y": 0.13422464515079247
          }
        },
        {
          "coord": {
            "x": 0.8909922363215126,
            "y": 0.5499879144606719
          }
        }
      ]
    },
    {
      "piece": 1,
      "corners": [
        {
          "coord": {
            "x": 0.09490194421919651,
            "y": -0.10065098361258251
          }
        },
        {
          "coord": {
            "x": 1.1645341543722338,
            "y": 0.08401763520799704
          }
        },
        {
          "coord": {
            "x": 1.0641480880842142,
            "y": 0.5914811800075837
          }
        },
        {
          "coord": {
            "x": 0.925399028026439,
            "y": 1.0575257454154872
          }
        },
        {
          "coord": {
            "x": -0.07522798579886059,
            "y": 0.8847706555409582
          }
        }
      ]
    },
    {
      "piece": 2,
      "corners": [
        {
          "coord": {
            "x": 0.03394488577219851,
            "y": 1.0536043004761546
          }
        },
        {
          "coord": {
            "x": -0.2174034683014519,
            "y": 0.3131623304858666
          }
        },
        {
          "coord": {
            "x": 0.30409042379584045,
            "y": 0.07399831078153457
          }
        },
        {
          "coord": {
            "x": 0.7151293582747309,
            "y": -0.050689854716866045
          }
        },
        {
          "coord": {
            "x": 1.0033834833776116,
            "y": 0.7984720705148496
          }
        },
        {
          "coord": {
            "x": 0.5276901711091764,
            "y": 0.8992922633149173
          }
        }
      ]
    }
  ]
}