{
  "puzzle": {
    "form": [
      {
        "coord": {
          "x": 0.0,
          "y": 0.0
        }
      },
      {
        "coord": {
          "x": 3.0,
          "y": 0.0
        }
      },
      {
        "coord": {
          "x": 3.0,
          "y": 3.0
        }
      },
      {
        "coord": {
          "x": 0.0,
          "y": 3.0
        }
      }
    ]
  },
  "name": "Puzzle-3r-3c-3756-sol.json",
  "no. of pieces": 9,
  "pieces": [
    {
      "piece": 0,
      "corners": [
        {
          "coord": {
            "x": 0.0,
            "y": 0.0
          }
        },
        {
          "coord": {
            "x": 0.31253005950835444,
            "y": 0.015266627577570802
          }
        },
        {
          "coord": {
            "x": 1.0059631455542795,
            "y": 0.037767201247502546
          }
        },
        {
          "coord": {
            "x": 0.7149757480480172,
            "y": 0.48020082273550435
          }
        },
        {
          "coord": {
            "x": 0.8944636252954272,
            "y": 1.0463515298903119
          }
        },
        {
          "coord": {
            "x": -0.273716238542525,
            "y": 1.0463515298903119
          }
        },
        {
          "coord": {
            "x": -0.03858037856654062,
            "y": 0.649267086890122
          }
        }
      ]
    },
    {
      "piece": 1,
      "corners": [
        {
          "coord": {
            "x": 0.0,
            "y": 0.0
          }
        },
        {
          "coord": {
            "x": 0.7065375556184279,
            "y": 0.0
          }
        },
        {
          "coord": {
            "x": 0.7240574594882863,
            "y": 0.4103984101749151
          }
        },
        {
          "coord": {
            "x": 1.0133025884985412,
            "y": 1.1057662066035057
          }
        },
        {
          "coord": {
            "x": 0.37683130105633866,
            "y": 0.9244476733863193
          }
        },
        {
          "coord": {
            "x": -0.0461182973178178,
            "y": 1.0927887317147544
          }
        },
        {
          "coord": {
            "x": 0.021941866883170125,
            "y": 0.5443164189734857
          }
        }
      ]
    },
    {
      "piece": 2,
      "corners": [
        {
          "coord": {
            "x": 0.0,
            "y": 0.0
          }
        },
        {
          "coord": {
            "x": 1.151046664852259,
            "y": 0.0
          }
        },
        {
          "coord": {
            "x": 1.151046664852259,
            "y": 1.0125704791086914
          }
        },
        {
          "coord": {
            "x": 0.7958130731066579,
            "y": 0.9178074292057067
          }
        },
        {
          "coord": {
            "x": 0.30676503288011325,
            "y": 1.1057662066035057
          }
        },
        {
          "coord": {
            "x": 0.017519903869858355,
            "y": 0.4103984101749151
          }
        }
      ]
    },
    {
      "piece": 3,
      "corners": [
        {
          "coord": {
            "x": 0.0,
            "y": 0.0
          }
        },
        {
          "coord": {
            "x": 0.22560666582730926,
            "y": -0.08045160541497043
          }
        },
        {
          "coord": {
            "x": 0.8829094992962707,
            "y": -0.08466750735230555
          }
        },
        {
          "coord": {
            "x": 0.8829094992962707,
            "y": 1.0085843286428093
          }
        },
        {
          "coord": {
            "x": -0.11149952025885224,
            "y": 1.0085843286428093
          }
        },
        {
          "coord": {
            "x": -0.29098739750626224,
            "y": 0.4424336214880018
          }
        }
      ]
    },
    {
      "piece": 4,
      "corners": [
        {
          "coord": {
            "x": 0.0,
            "y": 0.0
          }
        },
        {
          "coord": {
            "x": 0.42294959837415647,
            "y": -0.16834105832843516
          }
        },
        {
          "coord": {
            "x": 1.059420885816359,
            "y": 0.012977474888751228
          }
        },
        {
          "coord": {
            "x": 1.0311220775042884,
            "y": 0.43135179440784466
          }
        },
        {
          "coord": {
            "x": 1.020793018492234,
            "y": 0.8986269396424362
          }
        },
        {
          "coord": {
            "x": 0.327359932446309,
            "y": 0.8761263659725045
          }
        },
        {
          "coord": {
            "x": 0.014829872937954569,
            "y": 0.8608597383949337
          }
        },
        {
          "coord": {
            "x": -0.16002706181760384,
            "y": 0.293375637079174
          }
        }
      ]
    },
    {
      "piece": 5,
      "corners": [
        {
          "coord": {
            "x": 0.0,
            "y": 0.0
          }
        },
        {
          "coord": {
            "x": 0.5899337542066011,
            "y": 0.29777726588012143
          }
        },
        {
          "coord": {
            "x": 1.1111273551494498,
            "y": 0.12628604033599689
          }
        },
        {
          "coord": {
            "x": 1.0725469765829092,
            "y": 0.7755531272261189
          }
        },
        {
          "coord": {
            "x": 0.8374111166069248,
            "y": 1.1726375702263088
          }
        },
        {
          "coord": {
            "x": 0.0,
            "y": 1.1726375702263088
          }
        }
      ]
    },
    {
      "piece": 6,
      "corners": [
        {
          "coord": {
            "x": 0.0,
            "y": 0.0
          }
        },
        {
          "coord": {
            "x": 0.4890480402265447,
            "y": -0.18795877739779898
          }
        },
        {
          "coord": {
            "x": 0.8442816319721458,
            "y": -0.0931957274948143
          }
        },
        {
          "coord": {
            "x": 0.8442816319721458,
            "y": 0.8009819574013795
          }
        },
        {
          "coord": {
            "x": 0.18697879850318433,
            "y": 0.8051978593387146
          }
        },
        {
          "coord": {
            "x": -0.03862786732412493,
            "y": 0.885649464753685
          }
        },
        {
          "coord": {
            "x": -0.028298808312070545,
            "y": 0.41837431951909343
          }
        }
      ]
    },
    {
      "piece": 7,
      "corners": [
        {
          "coord": {
            "x": 0.0,
            "y": 0.0
          }
        },
        {
          "coord": {
            "x": 0.5604473723970169,
            "y": 0.13960043263174138
          }
        },
        {
          "coord": {
            "x": 1.0962974822114953,
            "y": 0.2424354536178075
          }
        },
        {
          "coord": {
            "x": 0.9362704203938914,
            "y": 0.5358110906969815
          }
        },
        {
          "coord": {
            "x": 1.1111273551494498,
            "y": 1.1032951920127412
          }
        },
        {
          "coord": {
            "x": 0.5899337542066011,
            "y": 1.2747864175568657
          }
        },
        {
          "coord": {
            "x": 0.0,
            "y": 0.9770091516767443
          }
        }
      ]
    },
    {
      "piece": 8,
      "corners": [
        {
          "coord": {
            "x": 0.0,
            "y": 0.0
          }
        },
        {
          "coord": {
            "x": 1.142415779529313,
            "y": 0.0
          }
        },
        {
          "coord": {
            "x": 1.1643576464124832,
            "y": 0.5443164189734857
          }
        },
        {
          "coord": {
            "x": 1.0962974822114953,
            "y": 1.0927887317147544
          }
        },
        {
          "coord": {
            "x": 0.5604473723970169,
            "y": 0.9899537107286883
          }
        },
        {
          "coord": {
            "x": 0.0,
            "y": 0.8503532780969469
          }
        }
      ]
    }
  ]
}