{
  "puzzle": {
    "form": [
      {
        "coord": {
          "x": 0.0,
          "y": 0.0
        }
      },
      {
        "coord": {
          "x": 3.0,
          "y": 0.0
        }
      },
      {
        "coord": {
          "x": 3.0,
          "y": 2.0
        }
      },
      {
        "coord": {
          "x": 0.0,
          "y": 2.0
        }
      }
    ]
  },
  "name": "Puzzle-5r-8c-6916.json",
  "no. of pieces": 40,
  "pieces": [
    {
      "piece": 0,
      "corners": [
        {
          "coord": {
            "x": 0.0,
            "y": 0.0
          }
        },
        {
          "coord": {
            "x": 0.08236168787357934,
            "y": 0.03755547789330438
          }
        },
        {
          "coord": {
            "x": 0.1890015660794332,
            "y": 0.04773045456017555
          }
        },
        {
          "coord": {
            "x": 0.2989686393359723,
            "y": 0.011567514217805441
          }
        },
        {
          "coord": {
            "x": 0.3519707580802529,
            "y": 0.021450450027463597
          }
        },
        {
          "coord": {
            "x": 0.40047245813047194,
            "y": 0.14292916424137792
          }
        },
        {
          "coord": {
            "x": 0.3646088895449531,
            "y": 0.19036125287982486
          }
        },
        {
          "coord": {
            "x": 0.38779919370858185,
            "y": 0.3308971024097569
          }
        },
        {
          "coord": {
            "x": 0.3780046336900811,
            "y": 0.42121437566881714
          }
        },
        {
          "coord": {
            "x": 0.30368522897080785,
            "y": 0.45168600511724377
          }
        },
        {
          "coord": {
            "x": 0.21389693129245568,
            "y": 0.3969589537966032
          }
        },
        {
          "coord": {
            "x": 0.05782377991698362,
            "y": 0.41224839924418766
          }
        },
        {
          "coord": {
            "x": -0.030819227725260134,
            "y": 0.4398752609018557
          }
        },
        {
          "coord": {
            "x": -0.010824481258735696,
            "y": 0.3167338888134421
          }
        },
        {
          "coord": {
            "x": -0.001515466173622193,
            "y": 0.19777369825869373
          }
        },
        {
          "coord": {
            "x": -0.005359443686160592,
            "y": 0.14369469040742766
          }
        }
      ]
    },
    {
      "piece": 1,
      "corners": [
        {
          "coord": {
            "x": 0.0,
            "y": 0.0
          }
        },
        {
          "coord": {
            "x": 0.1120646395236411,
            "y": -0.0047349038848572
          }
        },
        {
          "coord": {
            "x": 0.20186050198687666,
            "y": -0.011561608264945233
          }
        },
        {
          "coord": {
            "x": 0.28583407653233395,
            "y": 0.05027786687792202
          }
        },
        {
          "coord": {
            "x": 0.3618417241477292,
            "y": 0.0075792161138461545
          }
        },
        {
          "coord": {
            "x": 0.3381370212764858,
            "y": 0.15696334330191863
          }
        },
        {
          "coord": {
            "x": 0.37850777572845407,
            "y": 0.23948645483444797
          }
        },
        {
          "coord": {
            "x": 0.3787740985463477,
            "y": 0.3406836122572141
          }
        },
        {
          "coord": {
            "x": 0.3775501700272408,
            "y": 0.4173329441816793
          }
        },
        {
          "coord": {
            "x": 0.2576070887228574,
            "y": 0.4535831481658674
          }
        },
        {
          "coord": {
            "x": 0.15674417104409466,
            "y": 0.4270652543033042
          }
        },
        {
          "coord": {
            "x": 0.08901716500240253,
            "y": 0.4038044121977866
          }
        },
        {
          "coord": {
            "x": -0.033546720068913016,
            "y": 0.45513252620347755
          }
        },
        {
          "coord": {
            "x": -0.04412712079892289,
            "y": 0.3503019252325299
          }
        },
        {
          "coord": {
            "x": -1.2965324357483432E-4,
            "y": 0.24179087362143248
          }
        },
        {
          "coord": {
            "x": -0.03536409541520791,
            "y": 0.12626205487970776
          }
        }
      ]
    },
    {
      "piece": 2,
      "corners": [
        {
          "coord": {
            "x": 0.0,
            "y": 0.0
          }
        },
        {
          "coord": {
            "x": 0.1367336849142986,
            "y": 0.020380034418907123
          }
        },
        {
          "coord": {
            "x": 0.21966391244985184,
            "y": 0.010544629951411144
          }
        },
        {
          "coord": {
            "x": 0.3045905213780684,
            "y": 0.01415783381509983
          }
        },
        {
          "coord": {
            "x": 0.3904675255262453,
            "y": 0.020144755759784916
          }
        },
        {
          "coord": {
            "x": 0.3904675255262453,
            "y": 0.42043181877545877
          }
        },
        {
          "coord": {
            "x": 0.026595394008743334,
            "y": 0.42043181877545877
          }
        },
        {
          "coord": {
            "x": -0.006496701900881696,
            "y": 0.2973204307815469
          }
        },
        {
          "coord": {
            "x": 0.026157511004781142,
            "y": 0.2523827363610307
          }
        },
        {
          "coord": {
            "x": 0.04337844149002734,
            "y": 0.1536103711743737
          }
        }
      ]
    },
    {
      "piece": 3,
      "corners": [
        {
          "coord": {
            "x": 0.0,
            "y": 0.0
          }
        },
        {
          "coord": {
            "x": 0.10043508175947169,
            "y": 0.01684407435286972
          }
        },
        {
          "coord": {
            "x": 0.15676138218315616,
            "y": -0.005949569434775537
          }
        },
        {
          "coord": {
            "x": 0.23522906931370446,
            "y": 0.0023408522922818698
          }
        },
        {
          "coord": {
            "x": 0.35193742523920113,
            "y": -0.043617436498051276
          }
        },
        {
          "coord": {
            "x": 0.35193742523920113,
            "y": 0.385332469579005
          }
        },
        {
          "coord": {
            "x": 0.26606042109102424,
            "y": 0.37934554763431994
          }
        },
        {
          "coord": {
            "x": 0.18113381216280766,
            "y": 0.37573234377063125
          }
        },
        {
          "coord": {
            "x": 0.09820358462725443,
            "y": 0.38556774823812723
          }
        },
        {
          "coord": {
            "x": -0.03853010028704418,
            "y": 0.3651877138192201
          }
        },
        {
          "coord": {
            "x": -0.041994525184725795,
            "y": 0.3054231981609761
          }
        },
        {
          "coord": {
            "x": -4.8198294035284306E-4,
            "y": 0.20989755609944094
          }
        },
        {
          "coord": {
            "x": -0.048372097151510474,
            "y": 0.06624670885261796
          }
        }
      ]
    },
    {
      "piece": 4,
      "corners": [
        {
          "coord": {
            "x": 0.0,
            "y": 0.0
          }
        },
        {
          "coord": {
            "x": 0.04125184520969838,
            "y": 0.0028653283557373843
          }
        },
        {
          "coord": {
            "x": 0.1431791398023199,
            "y": -0.02324223150425553
          }
        },
        {
          "coord": {
            "x": 0.24071476791826396,
            "y": -0.025164147688355287
          }
        },
        {
          "coord": {
            "x": 0.32387894707541665,
            "y": 0.010585795359176808
          }
        },
        {
          "coord": {
            "x": 0.3311649245210313,
            "y": 0.06573362375758984
          }
        },
        {
          "coord": {
            "x": 0.33089588780554524,
            "y": 0.2046643199727145
          }
        },
        {
          "coord": {
            "x": 0.34928316988916297,
            "y": 0.3136325117175316
          }
        },
        {
          "coord": {
            "x": 0.3574205669680317,
            "y": 0.3788361226140706
          }
        },
        {
          "coord": {
            "x": -0.032453964612460195,
            "y": 0.3788361226140706
          }
        },
        {
          "coord": {
            "x": -0.02598614208722627,
            "y": 0.3112502636024128
          }
        },
        {
          "coord": {
            "x": -0.016222833754946153,
            "y": 0.20113015072135432
          }
        },
        {
          "coord": {
            "x": -0.045962852361240314,
            "y": 0.10495967629907366
          }
        }
      ]
    },
    {
      "piece": 5,
      "corners": [
        {
          "coord": {
            "x": 0.0,
            "y": 0.0
          }
        },
        {
          "coord": {
            "x": 0.04350207690317537,
            "y": -0.04208943525425024
          }
        },
        {
          "coord": {
            "x": 0.14458027015194547,
            "y": -0.0398134854787332
          }
        },
        {
          "coord": {
            "x": 0.28138400816854453,
            "y": -0.032635467049313416
          }
        },
        {
          "coord": {
            "x": 0.3534863552128194,
            "y": -0.04604288138125856
          }
        },
        {
          "coord": {
            "x": 0.3481269115266588,
            "y": 0.0976518090261691
          }
        },
        {
          "coord": {
            "x": 0.3519708890391972,
            "y": 0.15173081687743517
          }
        },
        {
          "coord": {
            "x": 0.3426618739540837,
            "y": 0.27069100743218355
          }
        },
        {
          "coord": {
            "x": 0.32266712748755927,
            "y": 0.39383237952059713
          }
        },
        {
          "coord": {
            "x": 0.2868622564659094,
            "y": 0.37970542725575296
          }
        },
        {
          "coord": {
            "x": 0.14504509876312993,
            "y": 0.3993949592930903
          }
        },
        {
          "coord": {
            "x": 0.07844306870472528,
            "y": 0.3768448385423797
          }
        },
        {
          "coord": {
            "x": 0.0016558202547884426,
            "y": 0.3590304840966676
          }
        },
        {
          "coord": {
            "x": -0.016107663790710103,
            "y": 0.2962385046734419
          }
        },
        {
          "coord": {
            "x": -0.010143375752646455,
            "y": 0.20393111302161837
          }
        },
        {
          "coord": {
            "x": -0.015879220981632636,
            "y": 0.05972886640098385
          }
        }
      ]
    },
    {
      "piece": 6,
      "corners": [
        {
          "coord": {
            "x": 0.0,
            "y": 0.0
          }
        },
        {
          "coord": {
            "x": 0.052157115124683795,
            "y": -0.02351366536564159
          }
        },
        {
          "coord": {
            "x": 0.17474858608365107,
            "y": -0.05851949972332826
          }
        },
        {
          "coord": {
            "x": 0.2491245449448214,
            "y": -0.06305189552932089
          }
        },
        {
          "coord": {
            "x": 0.38178711847991753,
            "y": -0.014427652038103034
          }
        },
        {
          "coord": {
            "x": 0.33341502132840706,
            "y": 0.05181905681451493
          }
        },
        {
          "coord": {
            "x": 0.3813051355395647,
            "y": 0.1954699040613379
          }
        },
        {
          "coord": {
            "x": 0.33979259329519174,
            "y": 0.29099554612287304
          }
        },
        {
          "coord": {
            "x": 0.34325701819287335,
            "y": 0.35076006178111707
          }
        },
        {
          "coord": {
            "x": 0.23834144742780028,
            "y": 0.3820847528047955
          }
        },
        {
          "coord": {
            "x": 0.1988269017095674,
            "y": 0.35391975760276684
          }
        },
        {
          "coord": {
            "x": 0.0461843138146425,
            "y": 0.33817933653221144
          }
        },
        {
          "coord": {
            "x": -0.014121328505128261,
            "y": 0.3560643124280187
          }
        },
        {
          "coord": {
            "x": 0.011756388847269594,
            "y": 0.29017635786703133
          }
        },
        {
          "coord": {
            "x": -0.03608411596426464,
            "y": 0.1398895767839592
          }
        },
        {
          "coord": {
            "x": 7.60487102281715E-4,
            "y": 0.07453660784017968
          }
        }
      ]
    },
    {
      "piece": 7,
      "corners": [
        {
          "coord": {
            "x": 0.0,
            "y": 0.0
          }
        },
        {
          "coord": {
            "x": 0.34640201922814917,
            "y": 0.0
          }
        },
        {
          "coord": {
            "x": 0.3830641895205007,
            "y": 0.12109657958064757
          }
        },
        {
          "coord": {
            "x": 0.33384317601251157,
            "y": 0.1940150560001031
          }
        },
        {
          "coord": {
            "x": 0.3466712168417896,
            "y": 0.29280448052238334
          }
        },
        {
          "coord": {
            "x": 0.38568838016312057,
            "y": 0.4186109371177581
          }
        },
        {
          "coord": {
            "x": 0.28026255310735726,
            "y": 0.36988621429477075
          }
        },
        {
          "coord": {
            "x": 0.13825964152798553,
            "y": 0.37153446873898616
          }
        },
        {
          "coord": {
            "x": 0.09530464005203676,
            "y": 0.41793648222104607
          }
        },
        {
          "coord": {
            "x": -0.021618207300619474,
            "y": 0.4085882416629082
          }
        },
        {
          "coord": {
            "x": -0.020561003775636966,
            "y": 0.3056660258808127
          }
        },
        {
          "coord": {
            "x": -0.01751330253514194,
            "y": 0.2123660519565917
          }
        },
        {
          "coord": {
            "x": -0.03127602176905864,
            "y": 0.13068445986403496
          }
        }
      ]
    },
    {
      "piece": 8,
      "corners": [
        {
          "coord": {
            "x": 0.0,
            "y": 0.0
          }
        },
        {
          "coord": {
            "x": 0.08864300764224375,
            "y": -0.027626861657668034
          }
        },
        {
          "coord": {
            "x": 0.24471615901771582,
            "y": -0.042916307105252516
          }
        },
        {
          "coord": {
            "x": 0.334504456696068,
            "y": 0.01181074421538808
          }
        },
        {
          "coord": {
            "x": 0.4088238614153412,
            "y": -0.01866088523303855
          }
        },
        {
          "coord": {
            "x": 0.3702690926483141,
            "y": 0.11352715322659268
          }
        },
        {
          "coord": {
            "x": 0.40106745960852774,
            "y": 0.18909583285767217
          }
        },
        {
          "coord": {
            "x": 0.40565469176156665,
            "y": 0.30484388161691567
          }
        },
        {
          "coord": {
            "x": 0.4301768537318267,
            "y": 0.40162077060606505
          }
        },
        {
          "coord": {
            "x": 0.27441507299740275,
            "y": 0.36079020772799364
          }
        },
        {
          "coord": {
            "x": 0.20259952116999413,
            "y": 0.4062350799133343
          }
        },
        {
          "coord": {
            "x": 0.12107011764081255,
            "y": 0.39015295380693726
          }
        },
        {
          "coord": {
            "x": 0.014755018728758174,
            "y": 0.40706686319069396
          }
        },
        {
          "coord": {
            "x": 0.03053353622024968,
            "y": 0.3081942822454009
          }
        },
        {
          "coord": {
            "x": 0.029492069262511245,
            "y": 0.21515085435278936
          }
        },
        {
          "coord": {
            "x": 0.045785316593411896,
            "y": 0.09236554365569716
          }
        }
      ]
    },
    {
      "piece": 9,
      "corners": [
        {
          "coord": {
            "x": 0.0,
            "y": 0.0
          }
        },
        {
          "coord": {
            "x": 0.11692284735265623,
            "y": 0.009348240558137877
          }
        },
        {
          "coord": {
            "x": 0.159877848828605,
            "y": -0.037053772923922035
          }
        },
        {
          "coord": {
            "x": 0.30188076040797673,
            "y": -0.03870202736813744
          }
        },
        {
          "coord": {
            "x": 0.40730658746374004,
            "y": 0.010022695454849906
          }
        },
        {
          "coord": {
            "x": 0.35595660778998583,
            "y": 0.1254240005629712
          }
        },
        {
          "coord": {
            "x": 0.35339643813794064,
            "y": 0.16535799677685592
          }
        },
        {
          "coord": {
            "x": 0.40989467872614593,
            "y": 0.2703684081008898
          }
        },
        {
          "coord": {
            "x": 0.4023074699994109,
            "y": 0.41489050243434844
          }
        },
        {
          "coord": {
            "x": 0.2941880400425232,
            "y": 0.41372674390059816
          }
        },
        {
          "coord": {
            "x": 0.19472586903717604,
            "y": 0.39040690668409406
          }
        },
        {
          "coord": {
            "x": 0.11213564926858277,
            "y": 0.39270119495580624
          }
        },
        {
          "coord": {
            "x": -0.007429154040517805,
            "y": 0.3922655990613634
          }
        },
        {
          "coord": {
            "x": 0.0346305307810475,
            "y": 0.30605028463098327
          }
        },
        {
          "coord": {
            "x": -0.0015108795077583004,
            "y": 0.2011832286016727
          }
        },
        {
          "coord": {
            "x": 0.014064930420106592,
            "y": 0.06201205425903611
          }
        }
      ]
    },
    {
      "piece": 10,
      "corners": [
        {
          "coord": {
            "x": 0.0,
            "y": 0.0
          }
        },
        {
          "coord": {
            "x": 0.08234498846425087,
            "y": -0.0016991534408264952
          }
        },
        {
          "coord": {
            "x": 0.17886122085664002,
            "y": -0.012090857156067836
          }
        },
        {
          "coord": {
            "x": 0.24027336898854612,
            "y": 0.031157820551017124
          }
        },
        {
          "coord": {
            "x": 0.3236366259829664,
            "y": 0.011723122525679752
          }
        },
        {
          "coord": {
            "x": 0.3712904453446191,
            "y": 0.11981433490731297
          }
        },
        {
          "coord": {
            "x": 0.3387356097685432,
            "y": 0.19967905959337107
          }
        },
        {
          "coord": {
            "x": 0.35903529161704273,
            "y": 0.2976142323692229
          }
        },
        {
          "coord": {
            "x": 0.3486891444222744,
            "y": 0.38882394319733005
          }
        },
        {
          "coord": {
            "x": 0.27268149680687914,
            "y": 0.4315225939614059
          }
        },
        {
          "coord": {
            "x": 0.18870792226142186,
            "y": 0.36968311881853866
          }
        },
        {
          "coord": {
            "x": 0.09891205979818629,
            "y": 0.3765098231986267
          }
        },
        {
          "coord": {
            "x": -0.013152579725454805,
            "y": 0.3812447270834839
          }
        },
        {
          "coord": {
            "x": -0.004233872312570552,
            "y": 0.29173440489508684
          }
        },
        {
          "coord": {
            "x": -0.054948575464355054,
            "y": 0.22451863973865238
          }
        },
        {
          "coord": {
            "x": -0.04417632868836274,
            "y": 0.07530251611243122
          }
        }
      ]
    },
    {
      "piece": 11,
      "corners": [
        {
          "coord": {
            "x": 0.0,
            "y": 0.0
          }
        },
        {
          "coord": {
            "x": 0.1127313535384391,
            "y": -0.011384653689539725
          }
        },
        {
          "coord": {
            "x": 0.1790575161284924,
            "y": -0.036616817665497126
          }
        },
        {
          "coord": {
            "x": 0.2855627782294907,
            "y": -0.06940006550374994
          }
        },
        {
          "coord": {
            "x": 0.34316840711128593,
            "y": -0.03549588889044408
          }
        },
        {
          "coord": {
            "x": 0.33402962689869087,
            "y": 0.03262459072967194
          }
        },
        {
          "coord": {
            "x": 0.3956604215646544,
            "y": 0.13722819753544224
          }
        },
        {
          "coord": {
            "x": 0.37161593119297165,
            "y": 0.28027636615704343
          }
        },
        {
          "coord": {
            "x": 0.3915898153630164,
            "y": 0.3606268742353951
          }
        },
        {
          "coord": {
            "x": 0.26070577734016953,
            "y": 0.3787346595843202
          }
        },
        {
          "coord": {
            "x": 0.1751520303450842,
            "y": 0.387358195131685
          }
        },
        {
          "coord": {
            "x": 0.05235634154937552,
            "y": 0.37761196920001483
          }
        },
        {
          "coord": {
            "x": -0.0263752994330817,
            "y": 0.36637275068272257
          }
        },
        {
          "coord": {
            "x": -0.026833894122754165,
            "y": 0.280816302969521
          }
        },
        {
          "coord": {
            "x": -0.021049972139665973,
            "y": 0.13977415987799735
          }
        },
        {
          "coord": {
            "x": 0.003775661819362064,
            "y": 0.059258255539553606
          }
        }
      ]
    },
    {
      "piece": 12,
      "corners": [
        {
          "coord": {
            "x": 0.0,
            "y": 0.0
          }
        },
        {
          "coord": {
            "x": 0.34615973221757357,
            "y": 0.0
          }
        },
        {
          "coord": {
            "x": 0.3650025771570342,
            "y": 0.13091078171172396
          }
        },
        {
          "coord": {
            "x": 0.35902214354030404,
            "y": 0.19101313926438418
          }
        },
        {
          "coord": {
            "x": 0.32162905231580163,
            "y": 0.29593582073210056
          }
        },
        {
          "coord": {
            "x": 0.35475599319731255,
            "y": 0.4334994986219958
          }
        },
        {
          "coord": {
            "x": 0.24716703791299488,
            "y": 0.3956814384872527
          }
        },
        {
          "coord": {
            "x": 0.1688365894968793,
            "y": 0.406330294773245
          }
        },
        {
          "coord": {
            "x": 0.10412062617967455,
            "y": 0.42220197262773584
          }
        },
        {
          "coord": {
            "x": -0.04428736849392445,
            "y": 0.3992496563323056
          }
        },
        {
          "coord": {
            "x": -0.027090716356038325,
            "y": 0.307322579573779
          }
        },
        {
          "coord": {
            "x": -0.04813191281513318,
            "y": 0.21394628448265252
          }
        },
        {
          "coord": {
            "x": -0.002729322442460269,
            "y": 0.12560201834773824
          }
        }
      ]
    },
    {
      "piece": 13,
      "corners": [
        {
          "coord": {
            "x": 0.0,
            "y": 0.0
          }
        },
        {
          "coord": {
            "x": 0.06030564231977076,
            "y": -0.017884975895807287
          }
        },
        {
          "coord": {
            "x": 0.21294823021469567,
            "y": -0.0021445548252518876
          }
        },
        {
          "coord": {
            "x": 0.25246277593292854,
            "y": 0.026020440376776754
          }
        },
        {
          "coord": {
            "x": 0.3573783466980016,
            "y": -0.005304250646901654
          }
        },
        {
          "coord": {
            "x": 0.40075678818802896,
            "y": 0.14830612052747205
          }
        },
        {
          "coord": {
            "x": 0.38353585770278276,
            "y": 0.24707848571412905
          }
        },
        {
          "coord": {
            "x": 0.3508816447971199,
            "y": 0.29201618013464525
          }
        },
        {
          "coord": {
            "x": 0.38397374070674495,
            "y": 0.4151275681285571
          }
        },
        {
          "coord": {
            "x": -0.016637876642898064,
            "y": 0.4151275681285571
          }
        },
        {
          "coord": {
            "x": 0.023803035845635367,
            "y": 0.28751592381994695
          }
        },
        {
          "coord": {
            "x": -0.00560154556893,
            "y": 0.2010684267668137
          }
        },
        {
          "coord": {
            "x": 0.006297436183127392,
            "y": 0.09248051643972977
          }
        }
      ]
    },
    {
      "piece": 14,
      "corners": [
        {
          "coord": {
            "x": 0.0,
            "y": 0.0
          }
        },
        {
          "coord": {
            "x": 0.1123751169460975,
            "y": 0.005467702349036929
          }
        },
        {
          "coord": {
            "x": 0.19636637297320905,
            "y": -0.005061667568413419
          }
        },
        {
          "coord": {
            "x": 0.28041112848769745,
            "y": 0.01988009890477449
          }
        },
        {
          "coord": {
            "x": 0.39499540498463037,
            "y": 0.020927250435158695
          }
        },
        {
          "coord": {
            "x": 0.3821975814176031,
            "y": 0.09740840597580308
          }
        },
        {
          "coord": {
            "x": 0.4031976240385991,
            "y": 0.20347319572549888
          }
        },
        {
          "coord": {
            "x": 0.3874582449426521,
            "y": 0.3018464490834741
          }
        },
        {
          "coord": {
            "x": 0.4019245766520431,
            "y": 0.4184338137152038
          }
        },
        {
          "coord": {
            "x": 0.2487256350220239,
            "y": 0.382757059007281
          }
        },
        {
          "coord": {
            "x": 0.20119418802984002,
            "y": 0.3839233612843001
          }
        },
        {
          "coord": {
            "x": 0.07614487229805503,
            "y": 0.3800401764198427
          }
        },
        {
          "coord": {
            "x": 0.0,
            "y": 0.405322904818945
          }
        }
      ]
    },
    {
      "piece": 15,
      "corners": [
        {
          "coord": {
            "x": 0.0,
            "y": 0.0
          }
        },
        {
          "coord": {
            "x": 0.11956480330910058,
            "y": 4.3559589444286395E-4
          }
        },
        {
          "coord": {
            "x": 0.20215502307769384,
            "y": -0.001858692377269322
          }
        },
        {
          "coord": {
            "x": 0.301617194083041,
            "y": 0.02146114483923478
          }
        },
        {
          "coord": {
            "x": 0.4097366240399287,
            "y": 0.02262490337298506
          }
        },
        {
          "coord": {
            "x": 0.38175434658123963,
            "y": 0.11170813075713582
          }
        },
        {
          "coord": {
            "x": 0.37883454734567623,
            "y": 0.17730794517007809
          }
        },
        {
          "coord": {
            "x": 0.35426861592339387,
            "y": 0.28068904511954407
          }
        },
        {
          "coord": {
            "x": 0.40904669419845163,
            "y": 0.41352662668104956
          }
        },
        {
          "coord": {
            "x": 0.2763841206633555,
            "y": 0.3649023831898317
          }
        },
        {
          "coord": {
            "x": 0.20200816180218517,
            "y": 0.36943477899582433
          }
        },
        {
          "coord": {
            "x": 0.0794166908432179,
            "y": 0.404440613353511
          }
        },
        {
          "coord": {
            "x": 0.0272595757185341,
            "y": 0.4279542787191526
          }
        },
        {
          "coord": {
            "x": 0.03385123327757711,
            "y": 0.286830846624722
          }
        },
        {
          "coord": {
            "x": 0.026660530451621867,
            "y": 0.1928361851409477
          }
        },
        {
          "coord": {
            "x": 0.020516193936150895,
            "y": 0.13055976459898821
          }
        }
      ]
    },
    {
      "piece": 16,
      "corners": [
        {
          "coord": {
            "x": 0.0,
            "y": 0.0
          }
        },
        {
          "coord": {
            "x": 0.148407994673599,
            "y": 0.022952316295430264
          }
        },
        {
          "coord": {
            "x": 0.21312395799080375,
            "y": 0.007080638440939424
          }
        },
        {
          "coord": {
            "x": 0.29145440640691933,
            "y": -0.003568217845052901
          }
        },
        {
          "coord": {
            "x": 0.399043361691237,
            "y": 0.03424984228969025
          }
        },
        {
          "coord": {
            "x": 0.40822437823755053,
            "y": 0.10595233537761395
          }
        },
        {
          "coord": {
            "x": 0.4196486429380759,
            "y": 0.21151517018853128
          }
        },
        {
          "coord": {
            "x": 0.42367190199496707,
            "y": 0.2869741935939314
          }
        },
        {
          "coord": {
            "x": 0.37205803423469685,
            "y": 0.4078458856515189
          }
        },
        {
          "coord": {
            "x": 0.2886947772402766,
            "y": 0.4272805836768563
          }
        },
        {
          "coord": {
            "x": 0.2272826291083705,
            "y": 0.3840319059697713
          }
        },
        {
          "coord": {
            "x": 0.13076639671598134,
            "y": 0.39442360968501267
          }
        },
        {
          "coord": {
            "x": 0.04842140825173047,
            "y": 0.39612276312583916
          }
        },
        {
          "coord": {
            "x": 0.028447524081685716,
            "y": 0.3157722550474875
          }
        },
        {
          "coord": {
            "x": 0.052492014453368485,
            "y": 0.17272408642588633
          }
        },
        {
          "coord": {
            "x": -0.009138780212595066,
            "y": 0.06812047962011603
          }
        }
      ]
    },
    {
      "piece": 17,
      "corners": [
        {
          "coord": {
            "x": 0.0,
            "y": 0.0
          }
        },
        {
          "coord": {
            "x": 0.359108710441774,
            "y": 0.0
          }
        },
        {
          "coord": {
            "x": 0.3621600035327985,
            "y": 0.08583016673816121
          }
        },
        {
          "coord": {
            "x": 0.37277512043412786,
            "y": 0.2338331480411266
          }
        },
        {
          "coord": {
            "x": 0.38007167804709785,
            "y": 0.26615795142813814
          }
        },
        {
          "coord": {
            "x": 0.39499540498463037,
            "y": 0.4282041639792221
          }
        },
        {
          "coord": {
            "x": 0.28041112848769745,
            "y": 0.4271570124488379
          }
        },
        {
          "coord": {
            "x": 0.19636637297320905,
            "y": 0.40221524597565
          }
        },
        {
          "coord": {
            "x": 0.1123751169460975,
            "y": 0.41274461589310035
          }
        },
        {
          "coord": {
            "x": 0.0,
            "y": 0.4072769135440634
          }
        }
      ]
    },
    {
      "piece": 18,
      "corners": [
        {
          "coord": {
            "x": 0.0,
            "y": 0.0
          }
        },
        {
          "coord": {
            "x": 0.06531059720320309,
            "y": -0.05611048314087064
          }
        },
        {
          "coord": {
            "x": 0.1391773011675932,
            "y": -0.012917745857581875
          }
        },
        {
          "coord": {
            "x": 0.22490255921973734,
            "y": -0.026373702417426204
          }
        },
        {
          "coord": {
            "x": 0.35124749539772404,
            "y": -0.05411744667167995
          }
        },
        {
          "coord": {
            "x": 0.35124749539772404,
            "y": 0.3472842868100132
          }
        },
        {
          "coord": {
            "x": 0.23453913947222738,
            "y": 0.39324257560034637
          }
        },
        {
          "coord": {
            "x": 0.15607145234167907,
            "y": 0.38495215387328896
          }
        },
        {
          "coord": {
            "x": 0.0997451519179946,
            "y": 0.4077457976609342
          }
        },
        {
          "coord": {
            "x": -6.899298414770882E-4,
            "y": 0.3909017233080645
          }
        },
        {
          "coord": {
            "x": -0.05546800811653485,
            "y": 0.258064141746559
          }
        },
        {
          "coord": {
            "x": -0.03090207669425249,
            "y": 0.15468304179709302
          }
        },
        {
          "coord": {
            "x": -0.027982277458689087,
            "y": 0.08908322738415075
          }
        }
      ]
    },
    {
      "piece": 19,
      "corners": [
        {
          "coord": {
            "x": 0.0,
            "y": 0.0
          }
        },
        {
          "coord": {
            "x": 0.1045313140531674,
            "y": -0.048427453263881315
          }
        },
        {
          "coord": {
            "x": 0.21023723985414577,
            "y": -0.052962035471276314
          }
        },
        {
          "coord": {
            "x": 0.2763146524827178,
            "y": 0.005237222406484554
          }
        },
        {
          "coord": {
            "x": 0.39223725797525444,
            "y": 0.005342341221670488
          }
        },
        {
          "coord": {
            "x": 0.3960129197946165,
            "y": 0.0646005967612241
          }
        },
        {
          "coord": {
            "x": 0.37118728583558847,
            "y": 0.14511650109966784
          }
        },
        {
          "coord": {
            "x": 0.3654033638525003,
            "y": 0.28615864419119147
          }
        },
        {
          "coord": {
            "x": 0.36586195854217274,
            "y": 0.37171509190439306
          }
        },
        {
          "coord": {
            "x": 0.3128598397978921,
            "y": 0.3618321560947349
          }
        },
        {
          "coord": {
            "x": 0.20289276654135302,
            "y": 0.397995096437105
          }
        },
        {
          "coord": {
            "x": 0.09625288833549916,
            "y": 0.38782011977023384
          }
        },
        {
          "coord": {
            "x": 0.013891200461919828,
            "y": 0.35026464187692946
          }
        },
        {
          "coord": {
            "x": -0.012608349300324173,
            "y": 0.28156517043372614
          }
        },
        {
          "coord": {
            "x": -0.01592205838492944,
            "y": 0.17594399259294052
          }
        },
        {
          "coord": {
            "x": 0.031424198022660055,
            "y": 0.08622514980212198
          }
        }
      ]
    },
    {
      "piece": 20,
      "corners": [
        {
          "coord": {
            "x": 0.0,
            "y": 0.0
          }
        },
        {
          "coord": {
            "x": 0.09973171633224948,
            "y": -0.023516452166894575
          }
        },
        {
          "coord": {
            "x": 0.154900622093471,
            "y": -0.046788798294621625
          }
        },
        {
          "coord": {
            "x": 0.2850587630363107,
            "y": -0.002947717525189908
          }
        },
        {
          "coord": {
            "x": 0.3465243264183123,
            "y": 0.0011990400218570563
          }
        },
        {
          "coord": {
            "x": 0.3779485244409724,
            "y": 0.08742418982397904
          }
        },
        {
          "coord": {
            "x": 0.3306022680333829,
            "y": 0.17714303261479758
          }
        },
        {
          "coord": {
            "x": 0.33391597711798815,
            "y": 0.2827642104555832
          }
        },
        {
          "coord": {
            "x": 0.36041552688023215,
            "y": 0.3514636818987865
          }
        },
        {
          "coord": {
            "x": 0.2883131798359573,
            "y": 0.36487109623073166
          }
        },
        {
          "coord": {
            "x": 0.15150944181935821,
            "y": 0.3576930778013119
          }
        },
        {
          "coord": {
            "x": 0.050431248570588116,
            "y": 0.35541712802579484
          }
        },
        {
          "coord": {
            "x": 0.006929171667412748,
            "y": 0.3975065632800451
          }
        },
        {
          "coord": {
            "x": -0.007537160041978297,
            "y": 0.2809191986483154
          }
        },
        {
          "coord": {
            "x": 0.008202219053968729,
            "y": 0.18254594529034018
          }
        },
        {
          "coord": {
            "x": -0.012797823567027244,
            "y": 0.07648115554064439
          }
        }
      ]
    },
    {
      "piece": 21,
      "corners": [
        {
          "coord": {
            "x": 0.0,
            "y": 0.0
          }
        },
        {
          "coord": {
            "x": 0.3647263061077574,
            "y": 0.0
          }
        },
        {
          "coord": {
            "x": 0.3953051107646309,
            "y": 0.1298685160604088
          }
        },
        {
          "coord": {
            "x": 0.3947473281255391,
            "y": 0.19205739853450152
          }
        },
        {
          "coord": {
            "x": 0.4110593449197261,
            "y": 0.32280156519658887
          }
        },
        {
          "coord": {
            "x": 0.3824110209611687,
            "y": 0.4294032040010792
          }
        },
        {
          "coord": {
            "x": 0.3209454575791671,
            "y": 0.4252564464540322
          }
        },
        {
          "coord": {
            "x": 0.19078731663632736,
            "y": 0.3814153656846005
          }
        },
        {
          "coord": {
            "x": 0.13561841087510584,
            "y": 0.40468771181232754
          }
        },
        {
          "coord": {
            "x": 0.03588669454285637,
            "y": 0.4282041639792221
          }
        },
        {
          "coord": {
            "x": 0.020962967605323846,
            "y": 0.26615795142813814
          }
        },
        {
          "coord": {
            "x": 0.013666409992353856,
            "y": 0.2338331480411266
          }
        },
        {
          "coord": {
            "x": 0.003051293091024476,
            "y": 0.08583016673816121
          }
        }
      ]
    },
    {
      "piece": 22,
      "corners": [
        {
          "coord": {
            "x": 0.0,
            "y": 0.0
          }
        },
        {
          "coord": {
            "x": 0.3781157316967836,
            "y": 0.0
          }
        },
        {
          "coord": {
            "x": 0.3753864092543233,
            "y": 0.12560201834773824
          }
        },
        {
          "coord": {
            "x": 0.3299838188816504,
            "y": 0.21394628448265252
          }
        },
        {
          "coord": {
            "x": 0.35102501534074526,
            "y": 0.307322579573779
          }
        },
        {
          "coord": {
            "x": 0.33382836320285914,
            "y": 0.3992496563323056
          }
        },
        {
          "coord": {
            "x": 0.2762227343210639,
            "y": 0.3653454797189997
          }
        },
        {
          "coord": {
            "x": 0.1697174722200656,
            "y": 0.39812872755725254
          }
        },
        {
          "coord": {
            "x": 0.1033913096300123,
            "y": 0.42336089153320994
          }
        },
        {
          "coord": {
            "x": -0.009340043908426798,
            "y": 0.43474554522274966
          }
        },
        {
          "coord": {
            "x": -0.01639245186360805,
            "y": 0.3015982804726214
          }
        },
        {
          "coord": {
            "x": -0.03502291429888049,
            "y": 0.19542789679757272
          }
        },
        {
          "coord": {
            "x": -0.028522791233623,
            "y": 0.11654751368132962
          }
        }
      ]
    },
    {
      "piece": 23,
      "corners": [
        {
          "coord": {
            "x": 0.0,
            "y": 0.0
          }
        },
        {
          "coord": {
            "x": 0.11695470859868332,
            "y": -0.03460306229604515
          }
        },
        {
          "coord": {
            "x": 0.18185215853296433,
            "y": -0.005544324723187
          }
        },
        {
          "coord": {
            "x": 0.25050284978583287,
            "y": -0.031114683586543235
          }
        },
        {
          "coord": {
            "x": 0.3966948500334634,
            "y": -0.018979830361264938
          }
        },
        {
          "coord": {
            "x": 0.37294353399960006,
            "y": 0.08266868270252026
          }
        },
        {
          "coord": {
            "x": 0.3422793813773232,
            "y": 0.17213028210312453
          }
        },
        {
          "coord": {
            "x": 0.34674749956384704,
            "y": 0.2638073987733758
          }
        },
        {
          "coord": {
            "x": 0.40471145099362527,
            "y": 0.39780517856232267
          }
        },
        {
          "coord": {
            "x": 0.0,
            "y": 0.39780517856232267
          }
        }
      ]
    },
    {
      "piece": 24,
      "corners": [
        {
          "coord": {
            "x": 0.0,
            "y": 0.0
          }
        },
        {
          "coord": {
            "x": 0.09988309524850472,
            "y": -0.01803284815035311
          }
        },
        {
          "coord": {
            "x": 0.19871009503289871,
            "y": 0.04625762548732326
          }
        },
        {
          "coord": {
            "x": 0.2728490048720616,
            "y": 0.04046124448585853
          }
        },
        {
          "coord": {
            "x": 0.40358039690683156,
            "y": -0.003009750524698429
          }
        },
        {
          "coord": {
            "x": 0.3622045919088399,
            "y": 0.08302172150109999
          }
        },
        {
          "coord": {
            "x": 0.3551564179510352,
            "y": 0.20742423994459624
          }
        },
        {
          "coord": {
            "x": 0.3460171829065085,
            "y": 0.3441202940508459
          }
        },
        {
          "coord": {
            "x": 0.3966948500334634,
            "y": 0.39546402919577917
          }
        },
        {
          "coord": {
            "x": 0.25050284978583287,
            "y": 0.38332917597050087
          }
        },
        {
          "coord": {
            "x": 0.18185215853296433,
            "y": 0.4088995348338571
          }
        },
        {
          "coord": {
            "x": 0.11695470859868332,
            "y": 0.37984079726099895
          }
        },
        {
          "coord": {
            "x": 0.0,
            "y": 0.4144438595570441
          }
        }
      ]
    },
    {
      "piece": 25,
      "corners": [
        {
          "coord": {
            "x": 0.0,
            "y": 0.0
          }
        },
        {
          "coord": {
            "x": 0.09947300113425217,
            "y": 0.0039893665754549
          }
        },
        {
          "coord": {
            "x": 0.2045890285884162,
            "y": 0.004925456446538412
          }
        },
        {
          "coord": {
            "x": 0.26868655815222064,
            "y": -0.011294463678835687
          }
        },
        {
          "coord": {
            "x": 0.3787786594608151,
            "y": -0.024265075005197145
          }
        },
        {
          "coord": {
            "x": 0.3434145640456072,
            "y": 0.10199697987451062
          }
        },
        {
          "coord": {
            "x": 0.3786490062172403,
            "y": 0.21752579861623533
          }
        },
        {
          "coord": {
            "x": 0.33465153866189223,
            "y": 0.32603685022733275
          }
        },
        {
          "coord": {
            "x": 0.3452319393919021,
            "y": 0.4308674511982804
          }
        },
        {
          "coord": {
            "x": 0.2620677602347494,
            "y": 0.3951175081507483
          }
        },
        {
          "coord": {
            "x": 0.16453213211880535,
            "y": 0.39703942433484807
          }
        },
        {
          "coord": {
            "x": 0.06260483752618384,
            "y": 0.423146984194841
          }
        },
        {
          "coord": {
            "x": 0.021352992316485464,
            "y": 0.4202816558391036
          }
        },
        {
          "coord": {
            "x": -0.0031691696537745617,
            "y": 0.3235047668499542
          }
        },
        {
          "coord": {
            "x": -0.007756401806813473,
            "y": 0.20775671809071072
          }
        },
        {
          "coord": {
            "x": -0.038554768767027126,
            "y": 0.13218803845963123
          }
        }
      ]
    },
    {
      "piece": 26,
      "corners": [
        {
          "coord": {
            "x": 0.0,
            "y": 0.0
          }
        },
        {
          "coord": {
            "x": 0.12256388507131555,
            "y": -0.05132811400569093
          }
        },
        {
          "coord": {
            "x": 0.19029089111300768,
            "y": -0.02806727190017333
          }
        },
        {
          "coord": {
            "x": 0.29115380879177044,
            "y": -0.0015493780376101274
          }
        },
        {
          "coord": {
            "x": 0.4110968900961538,
            "y": -0.03779958202179823
          }
        },
        {
          "coord": {
            "x": 0.37842508203912417,
            "y": 0.10315323697933532
          }
        },
        {
          "coord": {
            "x": 0.3783783179236988,
            "y": 0.178720005387363
          }
        },
        {
          "coord": {
            "x": 0.38987245381387003,
            "y": 0.27166743668116067
          }
        },
        {
          "coord": {
            "x": 0.3869299811463738,
            "y": 0.3682503272548938
          }
        },
        {
          "coord": {
            "x": 0.03354161989261506,
            "y": 0.3682503272548938
          }
        },
        {
          "coord": {
            "x": 0.025404222813746324,
            "y": 0.3030467163583548
          }
        },
        {
          "coord": {
            "x": 0.007016940730128596,
            "y": 0.1940785246135377
          }
        },
        {
          "coord": {
            "x": 0.007285977445614655,
            "y": 0.055147828398413035
          }
        }
      ]
    },
    {
      "piece": 27,
      "corners": [
        {
          "coord": {
            "x": 0.0,
            "y": 0.0
          }
        },
        {
          "coord": {
            "x": 0.09277022655592093,
            "y": 0.019884856675922213
          }
        },
        {
          "coord": {
            "x": 0.16039495920783198,
            "y": -0.02619953408170539
          }
        },
        {
          "coord": {
            "x": 0.2867135737421753,
            "y": -0.025145449537108622
          }
        },
        {
          "coord": {
            "x": 0.36240973273275356,
            "y": -0.009077658851865067
          }
        },
        {
          "coord": {
            "x": 0.36870716891588096,
            "y": 0.0834028575878647
          }
        },
        {
          "coord": {
            "x": 0.35680818716382356,
            "y": 0.19199076791494862
          }
        },
        {
          "coord": {
            "x": 0.38621276857838893,
            "y": 0.2784382649680819
          }
        },
        {
          "coord": {
            "x": 0.3457718560898555,
            "y": 0.40604990927669204
          }
        },
        {
          "coord": {
            "x": -0.02416690894978002,
            "y": 0.40604990927669204
          }
        },
        {
          "coord": {
            "x": -0.021224436282283765,
            "y": 0.3094670187029589
          }
        },
        {
          "coord": {
            "x": -0.032718572172454996,
            "y": 0.21651958740916122
          }
        },
        {
          "coord": {
            "x": -0.03267180805702963,
            "y": 0.14095281900113354
          }
        }
      ]
    },
    {
      "piece": 28,
      "corners": [
        {
          "coord": {
            "x": 0.0,
            "y": 0.0
          }
        },
        {
          "coord": {
            "x": 0.05392199963585942,
            "y": -0.013140719575943649
          }
        },
        {
          "coord": {
            "x": 0.1924744856817886,
            "y": 0.042122573852528156
          }
        },
        {
          "coord": {
            "x": 0.22868959754048768,
            "y": 0.01944565899478623
          }
        },
        {
          "coord": {
            "x": 0.3426518728348972,
            "y": 0.0433949788941459
          }
        },
        {
          "coord": {
            "x": 0.3453650632939441,
            "y": 0.12456209575806798
          }
        },
        {
          "coord": {
            "x": 0.3592550692609048,
            "y": 0.2384510573831562
          }
        },
        {
          "coord": {
            "x": 0.34263382319048774,
            "y": 0.3487396198493249
          }
        },
        {
          "coord": {
            "x": 0.3679324146351294,
            "y": 0.4167850089235876
          }
        },
        {
          "coord": {
            "x": 0.00801660096016188,
            "y": 0.4167850089235876
          }
        },
        {
          "coord": {
            "x": -0.04994735046961635,
            "y": 0.2827872291346407
          }
        },
        {
          "coord": {
            "x": -0.054415468656140165,
            "y": 0.19111011246438947
          }
        },
        {
          "coord": {
            "x": -0.023751316033863323,
            "y": 0.1016485130637852
          }
        }
      ]
    },
    {
      "piece": 29,
      "corners": [
        {
          "coord": {
            "x": 0.0,
            "y": 0.0
          }
        },
        {
          "coord": {
            "x": 0.10631509891205437,
            "y": -0.016913909383756698
          }
        },
        {
          "coord": {
            "x": 0.18784450244123596,
            "y": -8.317832773596656E-4
          }
        },
        {
          "coord": {
            "x": 0.2596600542686446,
            "y": -0.04627665546270032
          }
        },
        {
          "coord": {
            "x": 0.4154218350030685,
            "y": -0.005446092584628914
          }
        },
        {
          "coord": {
            "x": 0.3694589826418282,
            "y": 0.09951358371444474
          }
        },
        {
          "coord": {
            "x": 0.39919900124812235,
            "y": 0.1956840581367254
          }
        },
        {
          "coord": {
            "x": 0.38943569291584224,
            "y": 0.3058041710177839
          }
        },
        {
          "coord": {
            "x": 0.3829678703906083,
            "y": 0.3733900300294417
          }
        },
        {
          "coord": {
            "x": 0.025280541800232204,
            "y": 0.3733900300294417
          }
        },
        {
          "coord": {
            "x": -1.8049644409434684E-5,
            "y": 0.305344640955179
          }
        },
        {
          "coord": {
            "x": 0.016603196426007605,
            "y": 0.1950560784890103
          }
        },
        {
          "coord": {
            "x": 0.0027131904590469436,
            "y": 0.08116711686392208
          }
        }
      ]
    },
    {
      "piece": 30,
      "corners": [
        {
          "coord": {
            "x": 0.0,
            "y": 0.0
          }
        },
        {
          "coord": {
            "x": 0.07614487229805503,
            "y": -0.025282728399102283
          }
        },
        {
          "coord": {
            "x": 0.20119418802984002,
            "y": -0.021399543534644905
          }
        },
        {
          "coord": {
            "x": 0.2487256350220239,
            "y": -0.022565845811663987
          }
        },
        {
          "coord": {
            "x": 0.4019245766520431,
            "y": 0.013110908896258766
          }
        },
        {
          "coord": {
            "x": 0.3860453556704105,
            "y": 0.07283977529724261
          }
        },
        {
          "coord": {
            "x": 0.39178120089939666,
            "y": 0.21704202191787714
          }
        },
        {
          "coord": {
            "x": 0.385816912861333,
            "y": 0.3093494135697007
          }
        },
        {
          "coord": {
            "x": 0.40358039690683156,
            "y": 0.37214139299292637
          }
        },
        {
          "coord": {
            "x": 0.2728490048720616,
            "y": 0.4156123880034833
          }
        },
        {
          "coord": {
            "x": 0.19871009503289871,
            "y": 0.42140876900494806
          }
        },
        {
          "coord": {
            "x": 0.09988309524850472,
            "y": 0.3571182953672717
          }
        },
        {
          "coord": {
            "x": 0.0,
            "y": 0.3751511435176248
          }
        }
      ]
    },
    {
      "piece": 31,
      "corners": [
        {
          "coord": {
            "x": 0.0,
            "y": 0.0
          }
        },
        {
          "coord": {
            "x": 0.07873164098245722,
            "y": 0.01123921851729226
          }
        },
        {
          "coord": {
            "x": 0.2015273297781659,
            "y": 0.020985444448962443
          }
        },
        {
          "coord": {
            "x": 0.28708107677325123,
            "y": 0.012361908901597607
          }
        },
        {
          "coord": {
            "x": 0.4179651147960981,
            "y": -0.0057458764473274915
          }
        },
        {
          "coord": {
            "x": 0.37378878610773536,
            "y": 0.06955663966510373
          }
        },
        {
          "coord": {
            "x": 0.36301653933174305,
            "y": 0.2187727632913249
          }
        },
        {
          "coord": {
            "x": 0.41373124248352755,
            "y": 0.28598852844775935
          }
        },
        {
          "coord": {
            "x": 0.4048125350706433,
            "y": 0.3754988506361564
          }
        },
        {
          "coord": {
            "x": 0.2947204337620488,
            "y": 0.38846946196251786
          }
        },
        {
          "coord": {
            "x": 0.23062290419824438,
            "y": 0.40468938208789196
          }
        },
        {
          "coord": {
            "x": 0.12550687674408034,
            "y": 0.40375329221680845
          }
        },
        {
          "coord": {
            "x": 0.026033875609828172,
            "y": 0.39976392564135355
          }
        },
        {
          "coord": {
            "x": 0.035828435628328936,
            "y": 0.3094466523822933
          }
        },
        {
          "coord": {
            "x": 0.012638131464700164,
            "y": 0.16891080285236126
          }
        },
        {
          "coord": {
            "x": 0.04850170005021903,
            "y": 0.12147871421391432
          }
        }
      ]
    },
    {
      "piece": 32,
      "corners": [
        {
          "coord": {
            "x": 0.0,
            "y": 0.0
          }
        },
        {
          "coord": {
            "x": 0.08895781292546112,
            "y": -0.006971905319854255
          }
        },
        {
          "coord": {
            "x": 0.17445423212102074,
            "y": -0.005772012113545055
          }
        },
        {
          "coord": {
            "x": 0.3113263898904679,
            "y": -0.019476758656843896
          }
        },
        {
          "coord": {
            "x": 0.370476276422145,
            "y": -0.024911256959087635
          }
        },
        {
          "coord": {
            "x": 0.38454120684225157,
            "y": 0.037100797299948474
          }
        },
        {
          "coord": {
            "x": 0.3689653969143867,
            "y": 0.17627197164258507
          }
        },
        {
          "coord": {
            "x": 0.4051068072031925,
            "y": 0.28113902767189564
          }
        },
        {
          "coord": {
            "x": 0.3630471223816272,
            "y": 0.36735434210227574
          }
        },
        {
          "coord": {
            "x": 0.2642747529360838,
            "y": 0.3724504647987468
          }
        },
        {
          "coord": {
            "x": 0.18205180699539514,
            "y": 0.34598555556216776
          }
        },
        {
          "coord": {
            "x": 0.0711786026031751,
            "y": 0.37256075847577536
          }
        },
        {
          "coord": {
            "x": -0.026985327456540142,
            "y": 0.37359604336182867
          }
        },
        {
          "coord": {
            "x": 0.024628540303730073,
            "y": 0.25272435130424115
          }
        },
        {
          "coord": {
            "x": 0.020605281246838913,
            "y": 0.17726532789884103
          }
        },
        {
          "coord": {
            "x": 0.009181016546313536,
            "y": 0.0717024930879237
          }
        }
      ]
    },
    {
      "piece": 33,
      "corners": [
        {
          "coord": {
            "x": 0.0,
            "y": 0.0
          }
        },
        {
          "coord": {
            "x": 0.3855347388683663,
            "y": 0.0
          }
        },
        {
          "coord": {
            "x": 0.3855347388683663,
            "y": 0.4334509296123621
          }
        },
        {
          "coord": {
            "x": 0.3036030011186508,
            "y": 0.42331882522967323
          }
        },
        {
          "coord": {
            "x": 0.21003892994044993,
            "y": 0.38773959993157264
          }
        },
        {
          "coord": {
            "x": 0.13471327009534795,
            "y": 0.4186085786258673
          }
        },
        {
          "coord": {
            "x": 0.0392863609349714,
            "y": 0.4186109371177581
          }
        },
        {
          "coord": {
            "x": 2.6919761364041506E-4,
            "y": 0.29280448052238334
          }
        },
        {
          "coord": {
            "x": -0.012558843215637605,
            "y": 0.1940150560001031
          }
        },
        {
          "coord": {
            "x": 0.036662170292351526,
            "y": 0.12109657958064757
          }
        }
      ]
    },
    {
      "piece": 34,
      "corners": [
        {
          "coord": {
            "x": 0.0,
            "y": 0.0
          }
        },
        {
          "coord": {
            "x": 0.06467969871818102,
            "y": -0.006348590033665946
          }
        },
        {
          "coord": {
            "x": 0.18953904305909042,
            "y": 0.047260521485793294
          }
        },
        {
          "coord": {
            "x": 0.2790253652574166,
            "y": -0.006656856574633219
          }
        },
        {
          "coord": {
            "x": 0.3922395071173934,
            "y": 0.044611756787949375
          }
        },
        {
          "coord": {
            "x": 0.39299999421967513,
            "y": 0.11914836462812906
          }
        },
        {
          "coord": {
            "x": 0.3561553911531288,
            "y": 0.18450133357190857
          }
        },
        {
          "coord": {
            "x": 0.403995895964663,
            "y": 0.3347881146549807
          }
        },
        {
          "coord": {
            "x": 0.37811817861226515,
            "y": 0.4006760692159681
          }
        },
        {
          "coord": {
            "x": 0.3024220196216869,
            "y": 0.38460827853072455
          }
        },
        {
          "coord": {
            "x": 0.17610340508734357,
            "y": 0.3835541939861278
          }
        },
        {
          "coord": {
            "x": 0.10847867243543252,
            "y": 0.4296385847437554
          }
        },
        {
          "coord": {
            "x": 0.01570844587951159,
            "y": 0.40975372806783317
          }
        },
        {
          "coord": {
            "x": 0.0169323743986185,
            "y": 0.33310439614336795
          }
        },
        {
          "coord": {
            "x": 0.016666051580724872,
            "y": 0.23190723872060182
          }
        },
        {
          "coord": {
            "x": -0.023704702871243377,
            "y": 0.14938412718807248
          }
        }
      ]
    },
    {
      "piece": 35,
      "corners": [
        {
          "coord": {
            "x": 0.0,
            "y": 0.0
          }
        },
        {
          "coord": {
            "x": 0.07678724844993684,
            "y": 0.01781435444571211
          }
        },
        {
          "coord": {
            "x": 0.1433892785083415,
            "y": 0.04036447519642272
          }
        },
        {
          "coord": {
            "x": 0.28520643621112096,
            "y": 0.020674943159085357
          }
        },
        {
          "coord": {
            "x": 0.3210113072327708,
            "y": 0.03480189542392953
          }
        },
        {
          "coord": {
            "x": 0.3667966238261827,
            "y": 0.1271674390796267
          }
        },
        {
          "coord": {
            "x": 0.35050337649528207,
            "y": 0.24995274977671889
          }
        },
        {
          "coord": {
            "x": 0.3515448434530205,
            "y": 0.34299617766933044
          }
        },
        {
          "coord": {
            "x": 0.335766325961529,
            "y": 0.4418687586146235
          }
        },
        {
          "coord": {
            "x": 0.2218040506671195,
            "y": 0.4179194387152638
          }
        },
        {
          "coord": {
            "x": 0.18558893880842042,
            "y": 0.44059635357300575
          }
        },
        {
          "coord": {
            "x": 0.04703645276249124,
            "y": 0.38533306014453395
          }
        },
        {
          "coord": {
            "x": -0.006885546873368176,
            "y": 0.3984737797204776
          }
        },
        {
          "coord": {
            "x": -0.05756321400032305,
            "y": 0.3471300445755443
          }
        },
        {
          "coord": {
            "x": -0.048423978955796365,
            "y": 0.21043399046929467
          }
        },
        {
          "coord": {
            "x": -0.04137580499799165,
            "y": 0.08603147202579842
          }
        }
      ]
    },
    {
      "piece": 36,
      "corners": [
        {
          "coord": {
            "x": 0.0,
            "y": 0.0
          }
        },
        {
          "coord": {
            "x": 0.40069074470250343,
            "y": 0.0
          }
        },
        {
          "coord": {
            "x": 0.3694147229334448,
            "y": 0.13068445986403496
          }
        },
        {
          "coord": {
            "x": 0.3831774421673615,
            "y": 0.2123660519565917
          }
        },
        {
          "coord": {
            "x": 0.38012974092686647,
            "y": 0.3056660258808127
          }
        },
        {
          "coord": {
            "x": 0.37907253740188396,
            "y": 0.4085882416629082
          }
        },
        {
          "coord": {
            "x": 0.3199226508702069,
            "y": 0.41402273996515193
          }
        },
        {
          "coord": {
            "x": 0.18305049310075971,
            "y": 0.42772748650845077
          }
        },
        {
          "coord": {
            "x": 0.0975540739052001,
            "y": 0.42652759330214157
          }
        },
        {
          "coord": {
            "x": 0.008596260979738979,
            "y": 0.4334994986219958
          }
        },
        {
          "coord": {
            "x": -0.024530679901771935,
            "y": 0.29593582073210056
          }
        },
        {
          "coord": {
            "x": 0.012862411322730471,
            "y": 0.19101313926438418
          }
        },
        {
          "coord": {
            "x": 0.018842844939460646,
            "y": 0.13091078171172396
          }
        }
      ]
    },
    {
      "piece": 37,
      "corners": [
        {
          "coord": {
            "x": 0.0,
            "y": 0.0
          }
        },
        {
          "coord": {
            "x": 0.09542690916037655,
            "y": -2.358491890785963E-6
          }
        },
        {
          "coord": {
            "x": 0.17075256900547853,
            "y": -0.030871337186185455
          }
        },
        {
          "coord": {
            "x": 0.2643166401836794,
            "y": 0.004707888111915137
          }
        },
        {
          "coord": {
            "x": 0.3462483779333949,
            "y": 0.014839992494603993
          }
        },
        {
          "coord": {
            "x": 0.3462483779333949,
            "y": 0.3507503603078186
          }
        },
        {
          "coord": {
            "x": 0.2199034417554082,
            "y": 0.37849410456207233
          }
        },
        {
          "coord": {
            "x": 0.13417818370326406,
            "y": 0.39195006112191666
          }
        },
        {
          "coord": {
            "x": 0.06031147973887396,
            "y": 0.3487573238386279
          }
        },
        {
          "coord": {
            "x": -0.004999117464329128,
            "y": 0.40486780697949853
          }
        },
        {
          "coord": {
            "x": 0.0025880912624058894,
            "y": 0.2603457126460399
          }
        },
        {
          "coord": {
            "x": -0.053910149325799406,
            "y": 0.15533530132200601
          }
        },
        {
          "coord": {
            "x": -0.05134997967375421,
            "y": 0.1154013051081213
          }
        }
      ]
    },
    {
      "piece": 38,
      "corners": [
        {
          "coord": {
            "x": 0.0,
            "y": 0.0
          }
        },
        {
          "coord": {
            "x": 0.4192620167370925,
            "y": 0.0
          }
        },
        {
          "coord": {
            "x": 0.3907392255034695,
            "y": 0.11654751368132962
          }
        },
        {
          "coord": {
            "x": 0.384239102438212,
            "y": 0.19542789679757272
          }
        },
        {
          "coord": {
            "x": 0.40286956487348446,
            "y": 0.3015982804726214
          }
        },
        {
          "coord": {
            "x": 0.4099219728286657,
            "y": 0.43474554522274966
          }
        },
        {
          "coord": {
            "x": 0.2939993673361291,
            "y": 0.43464042640756373
          }
        },
        {
          "coord": {
            "x": 0.22792195470755705,
            "y": 0.37644116852980286
          }
        },
        {
          "coord": {
            "x": 0.12221602890657868,
            "y": 0.38097575073719786
          }
        },
        {
          "coord": {
            "x": 0.017684714853411276,
            "y": 0.4294032040010792
          }
        },
        {
          "coord": {
            "x": 0.04633303881196871,
            "y": 0.32280156519658887
          }
        },
        {
          "coord": {
            "x": 0.030021022017781673,
            "y": 0.19205739853450152
          }
        },
        {
          "coord": {
            "x": 0.03057880465687346,
            "y": 0.1298685160604088
          }
        }
      ]
    },
    {
      "piece": 39,
      "corners": [
        {
          "coord": {
            "x": 0.0,
            "y": 0.0
          }
        },
        {
          "coord": {
            "x": 0.09816393005971524,
            "y": -0.0010352848860533115
          }
        },
        {
          "coord": {
            "x": 0.20903713445193528,
            "y": -0.02761048779966091
          }
        },
        {
          "coord": {
            "x": 0.29126008039262397,
            "y": -0.0011455785630818394
          }
        },
        {
          "coord": {
            "x": 0.3900324498381673,
            "y": -0.006241701259552923
          }
        },
        {
          "coord": {
            "x": 0.4105486437743182,
            "y": 0.12431806333943529
          }
        },
        {
          "coord": {
            "x": 0.4166929802897892,
            "y": 0.18659448388139477
          }
        },
        {
          "coord": {
            "x": 0.4238836831157444,
            "y": 0.2805891453651691
          }
        },
        {
          "coord": {
            "x": 0.4172920255567014,
            "y": 0.42171257745959967
          }
        },
        {
          "coord": {
            "x": 0.3040778836967246,
            "y": 0.3704439640970171
          }
        },
        {
          "coord": {
            "x": 0.21459156149839842,
            "y": 0.4243613421574436
          }
        },
        {
          "coord": {
            "x": 0.08973221715748902,
            "y": 0.37075223063798435
          }
        },
        {
          "coord": {
            "x": 0.025052518439308002,
            "y": 0.3771008206716503
          }
        },
        {
          "coord": {
            "x": 0.03539866563407634,
            "y": 0.28589110984354316
          }
        },
        {
          "coord": {
            "x": 0.015098983785576836,
            "y": 0.18795593706769131
          }
        },
        {
          "coord": {
            "x": 0.047653819361652694,
            "y": 0.10809121238163322
          }
        }
      ]
    }
  ]
}