{
  "puzzle": {
    "form": [
      {
        "coord": {
          "x": 0.0,
          "y": 0.0
        }
      },
      {
        "coord": {
          "x": 3.0,
          "y": 0.0
        }
      },
      {
        "coord": {
          "x": 3.0,
          "y": 1.0
        }
      },
      {
        "coord": {
          "x": 0.0,
          "y": 1.0
        }
      }
    ]
  },
  "name": "Puzzle-1r-4c-5435-pure.json",
  "no. of pieces": 4,
  "pieces": [
    {
      "piece": 0,
      "corners": [
        {
          "coord": {
            "x": 0.8509345446017857,
            "y": 0.23776469878966988
          }
        },
        {
          "coord": {
            "x": 0.7856493372460769,
            "y": 1.0139811399213121
          }
        },
        {
          "coord": {
            "x": 0.1407613511832935,
            "y": 0.8517920905184113
          }
        },
        {
          "coord": {
            "x": -0.19864486815064764,
            "y": 0.7852658061211897
          }
        },
        {
          "coord": {
            "x": -0.1435990242860795,
            "y": 0.13079152696571772
          }
        },
        {
          "coord": {
            "x": 0.46188272842457456,
            "y": 0.040807238047051164
          }
        }
      ]
    },
    {
      "piece": 1,
      "corners": [
        {
          "coord": {
            "x": 0.041120141057382376,
            "y": 1.0720086598235623
          }
        },
        {
          "coord": {
            "x": -0.3112374656553954,
            "y": 0.3671293319172442
          }
        },
        {
          "coord": {
            "x": 0.5832313726482176,
            "y": -0.08000095927737527
          }
        },
        {
          "coord": {
            "x": 0.902464661746508,
            "y": 0.558614305380018
          }
        },
        {
          "coord": {
            "x": 0.5437385895900658,
            "y": 0.6987295838586118
          }
        }
      ]
    },
    {
      "piece": 2,
      "corners": [
        {
          "coord": {
            "x": -0.21282199927188727,
            "y": 0.5135994978466711
          }
        },
        {
          "coord": {
            "x": 0.28385966902804416,
            "y": -0.09566233515008549
          }
        },
        {
          "coord": {
            "x": 0.4937311785492053,
            "y": 0.2865777811436858
          }
        },
        {
          "coord": {
            "x": 1.0442543982988561,
            "y": 0.5542146800089978
          }
        },
        {
          "coord": {
            "x": 0.5622596493717078,
            "y": 1.1454605885429783
          }
        }
      ]
    },
    {
      "piece": 3,
      "corners": [
        {
          "coord": {
            "x": 0.8630985400217491,
            "y": 0.8469113996502619
          }
        },
        {
          "coord": {
            "x": 0.3119042974054825,
            "y": 1.1856075609259626
          }
        },
        {
          "coord": {
            "x": -0.1038425506344165,
            "y": 0.7175080718175699
          }
        },
        {
          "coord": {
            "x": -0.2747502340687583,
            "y": 0.37238888972096484
          }
        },
        {
          "coord": {
            "x": 0.4634569751410193,
            "y": -0.08122243030776322
          }
        },
        {
          "coord": {
            "x": 0.6111972414184974,
            "y": 0.23149971786616974
          }
        }
      ]
    }
  ]
}